kludge/__init__.py
kludge/__main__.py
kludge/app.py
kludge/cli.py
kludge/constants.py
kludge/klient.py
kludge/konfig.py
kludge/py.typed
kludge-0.0.1.dist-info/LICENSE
kludge-0.0.1.dist-info/METADATA
kludge-0.0.1.dist-info/WHEEL
kludge-0.0.1.dist-info/entry_points.txt
kludge-0.0.1.dist-info/RECORD
